tropic/__init__.py
tropic/engine/__init__.py
tropic/engine/const.py
tropic/linalg/mlmatrix.py
tropic/utils/__init__.py
tropic/utils/codecs/__init__.py
tropic/utils/codecs/hensel.py
tropic/utils/formats/__init__.py
tropic/utils/formats/number.py
tropic/utils/formats/sequence.py
tropic/utils/formats/string.py
tropic/utils/logger.py
tropic-0.2.5.dist-info/LICENSE
tropic-0.2.5.dist-info/WHEEL
tropic-0.2.5.dist-info/METADATA
tropic-0.2.5.dist-info/RECORD
